{
  "Kyep": {
    "title": "Case Closed",
    "day": 6,
    "time": "4:30 AM",
    "cover": "detective-conan-8d9a48d3dd",
    "streams": {
      "Amazon": "https://www.amazon.com/dp/B09Q2CH8RS",
      "Crunchyroll": "https://www.crunchyroll.com/case-closed",
      "Netflix": "https://www.netflix.com/title/80090370"
    }
  },
  "urTI": {
    "title": "One Piece",
    "day": 6,
    "time": "7:00 PM",
    "cover": "one-piece-f2f2a983a8",
    "streams": {
      "Crunchyroll": "https://www.crunchyroll.com/one-piece",
      "Funimation": "https://www.funimation.com/shows/one-piece/",
      "Hulu": "https://www.hulu.com/series/one-piece-c7a08df6-d0d5-4dd3-afff-d1f90133cd4e",
      "Netflix": "https://www.netflix.com/title/80107103"
    }
  },
  "NAVE": {
    "title": "Doraemon (2005)",
    "day": 6,
    "time": "12:00 AM",
    "cover": "doraemon-2005-371cbec0f6",
    "streams": {}
  },
  "ATJM": {
    "title": "Crayon Shin-chan",
    "day": 5,
    "time": "11:30 PM",
    "cover": "crayon-shin-chan-dc430f9db0",
    "streams": {}
  },
  "1C3r": {
    "title": "Sazae-san",
    "day": 7,
    "time": "1:30 AM",
    "cover": "sazae-san-162010bbcb",
    "streams": {}
  },
  "ziMS": {
    "title": "Ninjala",
    "day": 5,
    "time": "7:00 PM",
    "cover": "ninjala-c19a7f2bbe",
    "streams": {
      "HiDive": "https://www.hidive.com/tv/ninjala-the-animation"
    }
  },
  "eGsT": {
    "title": "PazuDora",
    "day": 7,
    "time": "1:00 AM",
    "cover": "pazudora-ca05e64b75",
    "streams": {}
  },
  "wrIz": {
    "title": "Yu\u2606Gi\u2606Oh! Go Rush!!",
    "day": 6,
    "time": "2:30 PM",
    "cover": "yu-gi-oh-go-rush-9ca7d7e015",
    "streams": {}
  },
  "dzBo": {
    "title": "Holo no Graffiti",
    "day": 7,
    "time": "1:01 AM",
    "cover": "holo-no-graffiti-95cd497081",
    "streams": {
      "YouTube": "https://www.youtube.com/playlist?list=PLb7AOG3cj7UyJfqsfXpvL2LUVdg0dOK7q"
    }
  },
  "vn9Y": {
    "title": "Tousouchuu: Great Mission",
    "day": 6,
    "time": "4:01 PM",
    "cover": "tousouchuu-great-mission-6eb5a16ca9",
    "streams": {},
    "status": true
  },
  "BkuV": {
    "title": "Pok\u00e9mon Horizons: The Series",
    "day": 5,
    "time": "1:55 AM",
    "cover": "pokemon-2023-273f1b2226",
    "streams": {},
    "status": true
  },
  "3CKQ": {
    "title": "Soaring Sky! Pretty Cure",
    "day": 6,
    "time": "6:30 PM",
    "cover": "hirogaru-sky-precure-0e14c3bfff",
    "streams": {
      "Crunchyroll": "https://www.crunchyroll.com/series/G0XHWM55N/soaring-sky-pretty-cure"
    }
  },
  "A9VI": {
    "title": "Sore Ike! Anpanman",
    "day": 4,
    "time": "5:55 PM",
    "cover": "sore-ike-anpanman-dbeb359c0e",
    "streams": {},
    "status": true
  },
  "PC6r": {
    "title": "Chibi Maruko-chan (1995)",
    "day": 7,
    "time": "1:00 AM",
    "cover": "chibi-maruko-chan-1995-04c12bc3f4",
    "streams": {},
    "status": true
  },
  "vkEQ": {
    "title": "Duel Masters Win: Duel Wars",
    "day": 6,
    "time": "3:30 PM",
    "cover": "duel-masters-win-duel-wars-aa7151ea18",
    "streams": {},
    "status": true
  },
  "Tav8": {
    "title": "Frieren: Beyond Journey's End",
    "day": 5,
    "time": "8:00 AM",
    "cover": "sousou-no-frieren-ec564ae1d9",
    "streams": {
      "Crunchyroll": "https://www.crunchyroll.com/series/GG5H5XQX4/frieren-beyond-journeys-end",
      "Netflix": "https://www.netflix.com/title/81726714",
      "YouTube": "https://www.youtube.com/playlist?list=PLwLSw1_eDZl10YPPR7qDsVf10wZfYnIMK"
    }
  },
  "oU6I": {
    "title": "Firefighter Daigo: Rescuer in Orange",
    "day": 6,
    "time": "2:00 AM",
    "cover": "megumi-no-daigo-kyuukoku-no-orange-8fa0cf605c",
    "streams": {
      "Crunchyroll": "https://www.crunchyroll.com/series/G0XHWM1MK/firefighter-daigo-rescuer-in-orange",
      "YouTube": "https://www.youtube.com/playlist?list=PLxSscENEp7JjUyg2zOamli_yuodl2aQFO"
    }
  },
  "6LIP": {
    "title": "Ragna Crimson",
    "day": 6,
    "time": "8:01 AM",
    "cover": "ragna-crimson-2f2fd638d0",
    "streams": {
      "Amazon": "https://www.primevideo.com/detail/Ragna-Crimson/0U5EZSNVUVMCD4Z0IGE1HHSFHW",
      "HiDive": "https://www.hidive.com/tv/ragna-crimson",
      "YouTube": "https://www.youtube.com/playlist?list=PLwLSw1_eDZl2gLJyLH6BkSr4l1XPaKDjT"
    }
  },
  "ehz5": {
    "title": "Shangri-La Frontier",
    "day": 7,
    "time": "2:30 AM",
    "cover": "shangri-la-frontier-80ff2650b9",
    "streams": {
      "Crunchyroll": "https://www.crunchyroll.com/series/G79H23Z8P/shangri-la-frontier",
      "YouTube": "https://www.youtube.com/playlist?list=PLwLSw1_eDZl1k3PpCugshhYpSQVWUAaib"
    }
  },
  "tG35": {
    "title": "Captain Tsubasa: Junior Youth Arc",
    "day": 7,
    "time": "2:00 AM",
    "cover": "captain-tsubasa-season-2-junior-youth-hen-17f2128c36",
    "streams": {
      "Crunchyroll": "https://www.crunchyroll.com/series/G4PH0WJDQ/captain-tsubasa-junior-youth-arc"
    }
  },
  "BQpb": {
    "title": "Undead Unluck",
    "day": 5,
    "time": "10:00 AM",
    "cover": "undead-unluck-d7a4b88861",
    "streams": {
      "Hulu": "https://www.hulu.com/series/undead-unluck-1e7b20f8-4f5c-46ab-8b24-fa2700a6c7a7"
    }
  },
  "MaIu": {
    "title": "The Seven Deadly Sins: Four Knights of the Apocalypse",
    "day": 6,
    "time": "11:30 PM",
    "cover": "nanatsu-no-taizai-mokushiroku-no-yonkishi-c2dc2c4491",
    "streams": {
      "Netflix": "https://www.netflix.com/title/81562396"
    }
  },
  "hZxw": {
    "title": "Odekake Kozame",
    "day": 2,
    "time": "3:00 AM",
    "cover": "odekake-kozame-315b850ca6",
    "streams": {
      "YouTube": "https://www.youtube.com/playlist?list=PLjrUB63ikczNcRItB8koEfoBfA7sjCZ-k"
    },
    "status": true
  },
  "DqGO": {
    "title": "Beyblade X",
    "day": 5,
    "time": "1:25 AM",
    "cover": "beyblade-x-f02b468b74",
    "streams": {},
    "status": true
  },
  "2TqS": {
    "title": "The Apothecary Diaries",
    "day": 6,
    "time": "11:05 AM",
    "cover": "kusuriya-no-hitorigoto-393de2094e",
    "streams": {
      "Crunchyroll": "https://www.crunchyroll.com/series/G3KHEVDJ7/the-apothecary-diaries",
      "Netflix": "https://www.netflix.com/title/81712068"
    }
  },
  "AbQz": {
    "title": "DOG SIGNAL",
    "day": 1,
    "time": "4:00 AM",
    "cover": "dog-signal-85e1172054",
    "streams": {
      "YouTube": "https://www.youtube.com/playlist?list=PLxSscENEp7JhSe-gomdI46wzX0lGWtLxv"
    },
    "status": true
  },
  "CivX": {
    "title": "I.CINNAMOROLL Animation",
    "day": 4,
    "time": "12:00 AM",
    "cover": "i-cinnamoroll-animation-6fa50ef829",
    "streams": {
      "YouTube": "https://www.youtube.com/playlist?list=PLe-UftTUsMbk7fMwURgLZ6_kz71DGssQw"
    },
    "status": true
  },
  "XvhE": {
    "title": "Kusuriya no Hitorigoto Mini Anime",
    "day": 7,
    "time": "7:00 PM",
    "cover": "maomao-no-hitorigoto-dc8e52e711",
    "streams": {
      "YouTube": "https://www.youtube.com/playlist?list=PLtdSPZNWT1AtlB6oZ-OLqZKXwMdMnIDiC"
    },
    "status": true
  },
  "7EQ3": {
    "title": "Xiaoke de Huatu Xie Hua",
    "day": 5,
    "time": "3:00 AM",
    "cover": "xiaoke-de-huatu-xie-hua-8dd81bea22",
    "streams": {
      "YouTube": "https://www.youtube.com/playlist?list=PLbuSQ8SJFnFH7D7_hwX94t-u3tyUxknsl"
    },
    "status": true
  },
  "WzQN": {
    "title": "Fluffy Paradise",
    "day": 7,
    "time": "7:00 AM",
    "cover": "isekai-de-mofumofu-nadenade-suru-tame-ni-ganbattemasu-54da17e73e",
    "streams": {
      "Crunchyroll": "https://www.crunchyroll.com/series/GZJH3D858/fluffy-paradise"
    }
  },
  "kkLK": {
    "title": "Ishura",
    "day": 3,
    "time": "6:30 AM",
    "cover": "ishura-dfe7952af3",
    "streams": {
      "Hulu": "https://www.hulu.com/series/ishura-811bac64-a492-4f1e-ba7a-393c825daeec"
    }
  },
  "ov61": {
    "title": "Classroom of the Elite",
    "day": 3,
    "time": "7:00 AM",
    "cover": "youkoso-jitsuryoku-shijou-shugi-no-kyoushitsu-e-3-20de2685fa",
    "streams": {
      "Crunchyroll": "https://www.crunchyroll.com/series/GRVN8MNQY/classroom-of-the-elite"
    }
  },
  "P98E": {
    "title": "Bottom-Tier Character Tomozaki",
    "day": 3,
    "time": "5:30 AM",
    "cover": "jaku-chara-tomozaki-kun-shin-e01104bac2",
    "streams": {
      "Crunchyroll": "https://www.crunchyroll.com/series/GDKHZEWP9/bottom-tier-character-tomozaki"
    }
  },
  "gM9F": {
    "title": "Gushing Over Magical Girls",
    "day": 3,
    "time": "8:00 AM",
    "cover": "mahou-shoujo-ni-akogarete-74fb58ce5d",
    "streams": {
      "HiDive": "https://www.hidive.com/tv/gushing-over-magical-girls"
    }
  },
  "lO3i": {
    "title": "Chained Soldier",
    "day": 4,
    "time": "7:00 AM",
    "cover": "mato-seihei-no-slave-4e7495e634",
    "streams": {
      "HiDive": "https://www.hidive.com/tv/chained-soldier"
    }
  },
  "9Jxh": {
    "title": "My Instant Death Ability is Overpowered",
    "day": 4,
    "time": "8:30 AM",
    "cover": "sokushi-cheat-ga-saikyou-sugite-isekai-no-yatsura-ga-marude-aite-ni-naranai-n-desu-ga-475c508dcb",
    "streams": {
      "HiDive": "https://www.hidive.com/tv/my-instant-death-ability-is-overpowered"
    }
  },
  "JN1Q": {
    "title": "Delicious in Dungeon",
    "day": 4,
    "time": "5:31 AM",
    "cover": "dungeon-meshi-4c1c47673a",
    "streams": {
      "Netflix": "https://www.netflix.com/title/81564899"
    }
  },
  "BBj5": {
    "title": "The Wrong Way to Use Healing Magic",
    "day": 5,
    "time": "9:00 AM",
    "cover": "chiyu-mahou-no-machigatta-tsukaikata-bb8cb97ae8",
    "streams": {
      "Crunchyroll": "https://www.crunchyroll.com/series/G0XHWM1EK/the-wrong-way-to-use-healing-magic"
    }
  },
  "uoDI": {
    "title": "Sasaki to Pi-chan",
    "day": 5,
    "time": "5:30 AM",
    "cover": "sasaki-to-pii-chan-5aa0c9e31b",
    "streams": {},
    "status": true
  },
  "4kON": {
    "title": "Pon no Michi",
    "day": 5,
    "time": "8:53 AM",
    "cover": "pon-no-michi-92669b5b1b",
    "streams": {},
    "status": true
  },
  "wloG": {
    "title": "The Demon Prince of Momochi House",
    "day": 5,
    "time": "8:30 AM",
    "cover": "momochi-san-chi-no-ayakashi-ouji-d4dc30c25c",
    "streams": {
      "Crunchyroll": "https://www.crunchyroll.com/series/GG5H5XQP4/the-demon-prince-of-momochi-house"
    }
  },
  "Qnd7": {
    "title": "Chou Futsuu Ken Chiba Densetsu",
    "day": 5,
    "time": "4:54 AM",
    "cover": "chou-futsuu-ken-chiba-densetsu-b05addf6bc",
    "streams": {},
    "status": true
  },
  "4DG1": {
    "title": "Solo Leveling",
    "day": 6,
    "time": "9:30 AM",
    "cover": "solo-leveling-bdca4ca63c",
    "streams": {
      "Crunchyroll": "https://www.crunchyroll.com/series/GDKHZEJ0K/solo-leveling"
    }
  },
  "gH3D": {
    "title": "MASHLE: MAGIC AND MUSCLES",
    "day": 6,
    "time": "8:00 AM",
    "cover": "mashle-2nd-season-cd64d078d4",
    "streams": {
      "Crunchyroll": "https://www.crunchyroll.com/series/GDKHZEP8W/mashle-magic-and-muscles"
    }
  },
  "qp4S": {
    "title": "Blue Exorcist",
    "day": 6,
    "time": "9:00 AM",
    "cover": "ao-no-exorcist-shin-series-7a55613191",
    "streams": {
      "Crunchyroll": "https://www.crunchyroll.com/series/G649PJ0JY/blue-exorcist"
    }
  },
  "nPeO": {
    "title": "The Dangers in My Heart",
    "day": 6,
    "time": "10:00 AM",
    "cover": "boku-no-kokoro-no-yabai-yatsu-2-09dce55f70",
    "streams": {
      "HiDive": "https://www.hidive.com/tv/the-dangers-in-my-heart/season-2"
    }
  },
  "frVv": {
    "title": "Tales of Wedding Rings",
    "day": 6,
    "time": "6:00 AM",
    "cover": "kekkon-yubiwa-monogatari-1da44db60f",
    "streams": {
      "Crunchyroll": "https://www.crunchyroll.com/series/G79H23ZGP/tales-of-wedding-rings",
      "YouTube": "https://www.youtube.com/playlist?list=PLxSscENEp7JgkXAKRkC3TZ53T9itBSZdQ"
    }
  },
  "nfpR": {
    "title": "Saikyou Tank no Meikyuu Kouryaku: Tairyoku 9999 no Rare Skill-mochi Tank, Yuusha Party wo Tsuihou Sareru",
    "day": 6,
    "time": "11:00 AM",
    "cover": "saikyou-tank-no-meikyuu-kouryaku-tairyoku-9999-no-rare-skill-mochi-tank-yuusha-party-wo-tsuihou-sareru-8165976e9c",
    "streams": {
      "YouTube": "https://www.youtube.com/playlist?list=PLxSscENEp7Ji3tb_Lb6OxaEz_cskN0WeZ"
    },
    "status": true
  },
  "DtSA": {
    "title": "A Sign of Affection",
    "day": 6,
    "time": "7:00 AM",
    "cover": "yubisaki-to-renren-ed73221abb",
    "streams": {
      "Crunchyroll": "https://www.crunchyroll.com/series/GEXH3W2V7/a-sign-of-affection",
      "YouTube": "https://www.youtube.com/playlist?list=PLwLSw1_eDZl14kD6iz4eILaU9kceG6UZL"
    }
  },
  "zlI8": {
    "title": "Kingdom 5",
    "day": 6,
    "time": "7:00 AM",
    "cover": "kingdom-5-75ec9c6105",
    "streams": {},
    "status": true
  },
  "pLOo": {
    "title": "Shin no Nakama ja Nai to Yuusha no Party wo Oidasareta node, Henkyou de Slow Life suru Koto ni shimashita 2nd Season",
    "day": 7,
    "time": "7:30 AM",
    "cover": "shin-no-nakama-ja-nai-to-yuusha-no-party-wo-oidasareta-node-henkyou-de-slow-life-suru-koto-ni-shimashita-2nd-season-344cb2a815",
    "streams": {},
    "status": true
  },
  "iQld": {
    "title": "7th Time Loop: The Villainess Enjoys a Carefree Life Married to Her Worst Enemy!",
    "day": 7,
    "time": "7:15 AM",
    "cover": "loop-7-kaime-no-akuyaku-reijou-wa-moto-tekikoku-de-jiyuu-kimama-na-hanayome-seikatsu-wo-mankitsu-suru-2afbf566e6",
    "streams": {
      "Crunchyroll": "https://www.crunchyroll.com/series/G4PH0WJGQ/7th-time-loop-the-villainess-enjoys-a-carefree-life-married-to-her-worst-enemy"
    }
  },
  "BE18": {
    "title": "Kyuujitsu no Warumono-san",
    "day": 7,
    "time": "10:45 AM",
    "cover": "kyuujitsu-no-warumono-san-65f4ee1d20",
    "streams": {},
    "status": true
  },
  "TueF": {
    "title": "The Unwanted Undead Adventurer",
    "day": 5,
    "time": "6:30 AM",
    "cover": "nozomanu-fushi-no-boukensha-4bf62a8e64",
    "streams": {
      "Crunchyroll": "https://www.crunchyroll.com/series/GW4HM7WZQ/the-unwanted-undead-adventurer"
    }
  },
  "Bglq": {
    "title": "Tsuki ga Michibiku Isekai Douchuu 2",
    "day": 1,
    "time": "6:00 AM",
    "cover": "tsuki-ga-michibiku-isekai-douchuu-2-17b31f3542",
    "streams": {},
    "status": true
  },
  "snqE": {
    "title": "Dosanko Gal wa Namara Menkoi",
    "day": 1,
    "time": "9:45 AM",
    "cover": "dosanko-gal-wa-namara-menkoi-890f2c3318",
    "streams": {},
    "status": true
  },
  "ZWTp": {
    "title": "Oroka na Tenshi wa Akuma to Odoru",
    "day": 1,
    "time": "8:30 AM",
    "cover": "oroka-na-tenshi-wa-akuma-to-odoru-98090010ae",
    "streams": {},
    "status": true
  },
  "3b31": {
    "title": "Hime-sama, \"Goumon\" no Jikan desu",
    "day": 1,
    "time": "7:00 AM",
    "cover": "hime-sama-goumon-no-jikan-desu-9f11b342c7",
    "streams": {},
    "status": true
  },
  "yydS": {
    "title": "HIGH CARD",
    "day": 1,
    "time": "3:00 AM",
    "cover": "high-card-season-2-582edf6cc7",
    "streams": {
      "Crunchyroll": "https://www.crunchyroll.com/series/G8DHV74W5/high-card"
    }
  },
  "c3OR": {
    "title": "SYNDUALITY Noir: Part 2",
    "day": 1,
    "time": "7:00 AM",
    "cover": "synduality-noir-part-2-ec9407983c",
    "streams": {},
    "status": true
  },
  "bxWG": {
    "title": "Akuyaku Reijou Level 99: Watashi wa Ura Boss desu ga Maou de wa Arimasen",
    "day": 2,
    "time": "6:30 AM",
    "cover": "akuyaku-reijou-level-99-watashi-wa-ura-boss-desu-ga-maou-dewa-arimasen-066d221855",
    "streams": {},
    "status": true
  },
  "odBF": {
    "title": "SHAMAN KING FLOWERS",
    "day": 2,
    "time": "7:00 AM",
    "cover": "shaman-king-zoku-hen-4498ae7b58",
    "streams": {},
    "status": true
  },
  "JPhm": {
    "title": "Sakigake!! Reiwa no Otokojuku",
    "day": 7,
    "time": "2:00 PM",
    "cover": "sakigake-reiwa-no-otokojuku-a1c343886f",
    "streams": {},
    "status": true
  },
  "vz76": {
    "title": "METALLIC ROUGE",
    "day": 3,
    "time": "7:55 AM",
    "cover": "metallic-rouge-886659320c",
    "streams": {},
    "status": true
  },
  "z2Nu": {
    "title": "Gekai Elise",
    "day": 3,
    "time": "4:30 AM",
    "cover": "gekai-elise-dea9c2953d",
    "streams": {},
    "status": true
  },
  "YUtR": {
    "title": "Sengoku Youko",
    "day": 3,
    "time": "7:00 AM",
    "cover": "sengoku-youko-7cd51c090d",
    "streams": {},
    "status": true
  },
  "CQ14": {
    "title": "30-sai made Doutei da to Mahou Tsukai ni Nareru Rashii",
    "day": 3,
    "time": "7:00 AM",
    "cover": "30-sai-made-doutei-dato-mahou-tsukai-ni-nareru-rashii-8a793f146b",
    "streams": {},
    "status": true
  },
  "2ZUg": {
    "title": "Majo to Yajuu",
    "day": 4,
    "time": "8:28 AM",
    "cover": "majo-to-yajuu-80e9baace2",
    "streams": {},
    "status": true
  },
  "2kDV": {
    "title": "Urusei Yatsura (2022) 2nd Season",
    "day": 4,
    "time": "7:55 AM",
    "cover": "urusei-yatsura-2022-2nd-season-6bcb315282",
    "streams": {},
    "status": true
  },
  "bXrT": {
    "title": "Gekkan Mousou Kagaku",
    "day": 4,
    "time": "6:30 AM",
    "cover": "gekkan-mousou-kagaku-791cedbf59",
    "streams": {},
    "status": true
  },
  "F2qe": {
    "title": "Yuuki Bakuhatsu Bang Bravern",
    "day": 4,
    "time": "6:56 AM",
    "cover": "yuuki-bakuhatsu-bang-bravern-22ee96834b",
    "streams": {},
    "status": true
  },
  "5ktD": {
    "title": "Saijaku Tamer wa Gomi Hiroi no Tabi wo Hajimemashita.",
    "day": 5,
    "time": "5:00 AM",
    "cover": "saijaku-tamer-wa-gomi-hiroi-no-tabi-wo-hajimemashita-230c11c860",
    "streams": {},
    "status": true
  },
  "TeYE": {
    "title": "Snack Basue",
    "day": 5,
    "time": "8:05 AM",
    "cover": "snack-basue-993665491f",
    "streams": {},
    "status": true
  },
  "Ehom": {
    "title": "Cardfight!! Vanguard: Divinez",
    "day": 5,
    "time": "3:00 PM",
    "cover": "cardfight-vanguard-overdress-season-6-b45b0ad000",
    "streams": {},
    "status": true
  },
  "54NC": {
    "title": "Bucchigiri?!",
    "day": 6,
    "time": "6:00 AM",
    "cover": "bucchigiri-2024-01a905e20c",
    "streams": {},
    "status": true
  },
  "AERt": {
    "title": "Yami Shibai 12",
    "day": 6,
    "time": "9:35 AM",
    "cover": "",
    "streams": {},
    "status": true
  },
  "xOW4": {
    "title": "Hikari no Ou 2nd Season",
    "day": 7,
    "time": "6:00 AM",
    "cover": "hikari-no-ou-2nd-season-7e0beecd91",
    "streams": {},
    "status": true
  },
  "datU": {
    "title": "Meiji Gekken: 1874",
    "day": 7,
    "time": "6:00 AM",
    "cover": "meiji-gekken-1874-a145c00f21",
    "streams": {},
    "status": true
  }
}